[
    {
        "ID": 10,
        "CreatedAt": "2026-04-27T07:07:07.276529Z",
        "UpdatedAt": "2026-04-27T07:07:50.290261Z",
        "DeletedAt": null,
        "UserID": 14,
        "Key": "the_doghouse",
        "Level": 1,
        "UpgradeCostDogCoins": 5,
        "UpgradeCostDogBones": 0,
        "UpgradeCostDogs": 0,
        "IsConstructing": true,
        "StartedAt": "2026-04-27T07:07:50.289635Z",
        "CompletesAt": "2026-04-27T07:08:20.289635Z"
    },
    {
        "ID": 11,
        "CreatedAt": "2026-04-27T07:08:14.080853Z",
        "UpdatedAt": "2026-04-27T07:08:14.080853Z",
        "DeletedAt": null,
        "UserID": 14,
        "Key": "dog_coin_den",
        "Level": 0,
        "UpgradeCostDogCoins": 500,
        "UpgradeCostDogBones": 100,
        "UpgradeCostDogs": 10,
        "IsConstructing": false,
        "StartedAt": null,
        "CompletesAt": null
    },
        {
        "ID": 12,
        "CreatedAt": "2026-04-27T07:08:14.080853Z",
        "UpdatedAt": "2026-04-27T07:08:14.080853Z",
        "DeletedAt": null,
        "UserID": 14,
        "Key": "kennel",
        "Level": 0,
        "UpgradeCostDogCoins": 5,
        "UpgradeCostDogBones": 0,
        "UpgradeCostDogs": 0,
        "IsConstructing": false,
        "StartedAt": null,
        "CompletesAt": null
    },
        {
        "ID": 13,
        "CreatedAt": "2026-04-27T07:08:14.080853Z",
        "UpdatedAt": "2026-04-27T07:08:14.080853Z",
        "DeletedAt": null,
        "UserID": 14,
        "Key": "market",
        "Level": 1,
        "UpgradeCostDogCoins": 5,
        "UpgradeCostDogBones": 0,
        "UpgradeCostDogs": 0,
        "IsConstructing": false,
        "StartedAt": null,
        "CompletesAt": null
    },
        {
        "ID": 14,
        "CreatedAt": "2026-04-27T07:08:14.080853Z",
        "UpdatedAt": "2026-04-27T07:08:14.080853Z",
        "DeletedAt": null,
        "UserID": 14,
        "Key": "dog_bone_factory",
        "Level": 0,
        "UpgradeCostDogCoins": 5,
        "UpgradeCostDogBones": 0,
        "UpgradeCostDogs": 0,
        "IsConstructing": false,
        "StartedAt": null,
        "CompletesAt": null
    }
]
